README.rst
setup.py
ooservice/__init__.py
ooservice.egg-info/PKG-INFO
ooservice.egg-info/SOURCES.txt
ooservice.egg-info/dependency_links.txt
ooservice.egg-info/requires.txt
ooservice.egg-info/top_level.txt