Metadata-Version: 1.1
Name: ooservice
Version: 0.2.0
Summary: OpenERP Service
Home-page: http://www.gisce.net
Author: GISCE-TI, S.L.
Author-email: devel@gisce.net
License: General Public Licence 2
Platform: UNKNOWN
Provides: ooservice
